flet_textfield_extras/__init__.py
flet_textfield_extras/flet_textfield_extras.py
flutter/flet_textfield_extras/CHANGELOG.md
flutter/flet_textfield_extras/LICENSE
flutter/flet_textfield_extras/README.md
flutter/flet_textfield_extras/pubspec.yaml
flutter/flet_textfield_extras/lib/flet_textfield_extras.dart
flutter/flet_textfield_extras/lib/src/create_control.dart
flutter/flet_textfield_extras/lib/src/flet_textfield_extras.dart
flet_textfield_extras-0.1.2.dist-info/METADATA
flet_textfield_extras-0.1.2.dist-info/WHEEL
flet_textfield_extras-0.1.2.dist-info/top_level.txt
flet_textfield_extras-0.1.2.dist-info/RECORD
