Metadata-Version: 2.4
Name: flet-textfield-extras
Version: 0.1.2
Summary: FletTextfieldExtras control for Flet
Author-email: Flet contributors <you@example.com>
Project-URL: Homepage, https://mydomain.dev
Project-URL: Documentation, https://github.com/MyGithubAccount/flet-textfield-extras
Project-URL: Repository, https://github.com/MyGithubAccount/flet-textfield-extras
Project-URL: Issues, https://github.com/MyGithubAccount/flet-textfield-extras/issues
Requires-Python: >=3.9
Requires-Dist: flet>=0.28.3
